pylit.py
pylit-0.8.0.dist-info/entry_points.txt
pylit-0.8.0.dist-info/LICENSE
pylit-0.8.0.dist-info/WHEEL
pylit-0.8.0.dist-info/METADATA
pylit-0.8.0.dist-info/RECORD
