Metadata-Version: 2.1
Name: pylit
Version: 0.8.0
Summary: pylit: bidirectional text <-> code converter
Home-page: https://codeberg.org/milde/pylit
License: UNKNOWN
Author: Günter Milde
Author-email: milde@users.sf.net
Requires-Python: >=2.7
Classifier: Intended Audience :: Developers
Classifier: License :: OSI Approved :: GNU General Public License v3 or later (GPLv3+)
Classifier: Development Status :: 4 - Beta
Classifier: Environment :: Console
Classifier: Topic :: Software Development :: Documentation
Requires-Dist: sphinx ; extra == "doc"
Requires-Dist: nose ; extra == "test"
Provides-Extra: doc
Provides-Extra: test
